{
	"animations": [
		{
			"offsets": [
				-5,
				-16
			],
			"loop": false,
			"fps": 24,
			"anim": "singDOWN",
			"indices": [],
			"name": "May NOTE DOWN"
		},
		{
			"offsets": [
				24,
				-1
			],
			"loop": false,
			"fps": 24,
			"anim": "singLEFT",
			"indices": [],
			"name": "May NOTE RIGHT"
		},
		{
			"offsets": [
				-48,
				-12
			],
			"loop": false,
			"fps": 24,
			"anim": "singRIGHT",
			"indices": [],
			"name": "May NOTE LEFT"
		},
		{
			"offsets": [
				-25,
				73
			],
			"loop": false,
			"fps": 24,
			"anim": "singUP",
			"indices": [],
			"name": "May NOTE UP"
		},
		{
			"offsets": [
				53,
				23
			],
			"loop": false,
			"fps": 24,
			"anim": "shoot",
			"indices": [],
			"name": "May ALT"
		},
		{
			"loop": false,
			"offsets": [
				32,
				0
			],
			"anim": "danceLeft",
			"fps": 24,
			"name": "May IdleRight SPRITE",
			"indices": []
		},
		{
			"loop": false,
			"offsets": [
				0,
				0
			],
			"anim": "danceRight",
			"fps": 24,
			"name": "May IdleLeft SPRITE",
			"indices": []
		}
	],
	"no_antialiasing": false,
	"image": "characters/week2/may",
	"position": [
		50,
		110
	],
	"healthicon": "may",
	"flip_x": true,
	"healthbar_colors": [
		115,
		40,
		255
	],
	"camera_position": [
		-200,
		-80
	],
	"sing_duration": 6.1,
	"scale": 1
}